plugwise/__init__.py
plugwise/constants.py
plugwise/exceptions.py
plugwise/message.py
plugwise/node.py
plugwise/parser.py
plugwise/stick.py
plugwise/util.py
plugwise/connections/__init__.py
plugwise/connections/connection.py
plugwise/connections/serial.py
plugwise/connections/socket.py
plugwise/messages/__init__.py
plugwise/messages/requests.py
plugwise/messages/responses.py
plugwise/nodes/__init__.py
plugwise/nodes/circle.py
plugwise/nodes/circle_plus.py
plugwise/nodes/scan.py
plugwise/nodes/sed.py
plugwise/nodes/sense.py
plugwise/nodes/stealth.py
plugwise/nodes/switch.py
python_plugwise-2.0.2.dist-info/LICENSE
python_plugwise-2.0.2.dist-info/METADATA
python_plugwise-2.0.2.dist-info/WHEEL
python_plugwise-2.0.2.dist-info/top_level.txt
python_plugwise-2.0.2.dist-info/RECORD
