Metadata-Version: 2.1
Name: python-plugwise
Version: 2.0.2
Summary: Async library for Plugwise USB-stick
Home-page: https://github.com/brefra/python-plugwise
Author: Frank van Breugel
Author-email: f.v.breugel@gmail.com
License: MIT
Keywords: home,plugwise,stick,automation
Platform: any
Classifier: Programming Language :: Python :: 3
Classifier: License :: OSI Approved :: MIT License
Classifier: Intended Audience :: Developers
Classifier: Natural Language :: English
Classifier: Operating System :: OS Independent
Classifier: Topic :: Home Automation
Requires-Python: >=3.6
Requires-Dist: crcmod
Requires-Dist: pyserial
